<?xml version="1.0" encoding="UTF-8"?>
<!DOCTYPE mapper PUBLIC "-//mybatis.org//DTD Mapper 3.0//EN" "http://mybatis.org/dtd/mybatis-3-mapper.dtd">
<mapper namespace="com.chawuzhi.novel.common.mapper.RecommendBookMapper">
  <resultMap id="BaseResultMap" type="com.chawuzhi.novel.common.domain.RecommendBook">
    <!--
      WARNING - @mbggenerated
      This element is automatically generated by MyBatis Generator, do not modify.
      This element was generated on Thu Oct 26 19:04:52 GMT+08:00 2017.
    -->
    <id column="id" jdbcType="INTEGER" property="id" />
    <result column="book_id" jdbcType="INTEGER" property="bookId" />
    <result column="position" jdbcType="INTEGER" property="position" />
    <result column="lay_position" jdbcType="VARCHAR" property="layPosition" />
    <result column="length_of_recommend" jdbcType="DATE" property="lengthOfRecommend" />
    <result column="creater_no" jdbcType="VARCHAR" property="createrNo" />
    <result column="create_time" jdbcType="TIMESTAMP" property="createTime" />
    <result column="modifier_no" jdbcType="VARCHAR" property="modifierNo" />
    <result column="modify_time" jdbcType="TIMESTAMP" property="modifyTime" />
  </resultMap>
  <sql id="Example_Where_Clause">
    <!--
      WARNING - @mbggenerated
      This element is automatically generated by MyBatis Generator, do not modify.
      This element was generated on Thu Oct 26 19:04:52 GMT+08:00 2017.
    -->
    <where>
      <foreach collection="oredCriteria" item="criteria" separator="or">
        <if test="criteria.valid">
          <trim prefix="(" prefixOverrides="and" suffix=")">
            <foreach collection="criteria.criteria" item="criterion">
              <choose>
                <when test="criterion.noValue">
                  and ${criterion.condition}
                </when>
                <when test="criterion.singleValue">
                  and ${criterion.condition} #{criterion.value}
                </when>
                <when test="criterion.betweenValue">
                  and ${criterion.condition} #{criterion.value} and #{criterion.secondValue}
                </when>
                <when test="criterion.listValue">
                  and ${criterion.condition}
                  <foreach close=")" collection="criterion.value" item="listItem" open="(" separator=",">
                    #{listItem}
                  </foreach>
                </when>
              </choose>
            </foreach>
          </trim>
        </if>
      </foreach>
    </where>
  </sql>
  <sql id="Update_By_Example_Where_Clause">
    <!--
      WARNING - @mbggenerated
      This element is automatically generated by MyBatis Generator, do not modify.
      This element was generated on Thu Oct 26 19:04:52 GMT+08:00 2017.
    -->
    <where>
      <foreach collection="example.oredCriteria" item="criteria" separator="or">
        <if test="criteria.valid">
          <trim prefix="(" prefixOverrides="and" suffix=")">
            <foreach collection="criteria.criteria" item="criterion">
              <choose>
                <when test="criterion.noValue">
                  and ${criterion.condition}
                </when>
                <when test="criterion.singleValue">
                  and ${criterion.condition} #{criterion.value}
                </when>
                <when test="criterion.betweenValue">
                  and ${criterion.condition} #{criterion.value} and #{criterion.secondValue}
                </when>
                <when test="criterion.listValue">
                  and ${criterion.condition}
                  <foreach close=")" collection="criterion.value" item="listItem" open="(" separator=",">
                    #{listItem}
                  </foreach>
                </when>
              </choose>
            </foreach>
          </trim>
        </if>
      </foreach>
    </where>
  </sql>
  <sql id="Base_Column_List">
    <!--
      WARNING - @mbggenerated
      This element is automatically generated by MyBatis Generator, do not modify.
      This element was generated on Thu Oct 26 19:04:52 GMT+08:00 2017.
    -->
    id, book_id, position, lay_position, length_of_recommend, creater_no, create_time, 
    modifier_no, modify_time
  </sql>
  <select id="selectByExample" parameterType="com.chawuzhi.novel.common.domain.RecommendBookExample" resultMap="BaseResultMap">
    <!--
      WARNING - @mbggenerated
      This element is automatically generated by MyBatis Generator, do not modify.
      This element was generated on Thu Oct 26 19:04:52 GMT+08:00 2017.
    -->
    select
    <if test="distinct">
      distinct
    </if>
    <include refid="Base_Column_List" />
    from recommend_book
    <if test="_parameter != null">
      <include refid="Example_Where_Clause" />
    </if>
    <if test="orderByClause != null">
      order by ${orderByClause}
    </if>
  </select>
  <select id="selectByPrimaryKey" parameterType="java.lang.Integer" resultMap="BaseResultMap">
    <!--
      WARNING - @mbggenerated
      This element is automatically generated by MyBatis Generator, do not modify.
      This element was generated on Thu Oct 26 19:04:52 GMT+08:00 2017.
    -->
    select 
    <include refid="Base_Column_List" />
    from recommend_book
    where id = #{id,jdbcType=INTEGER}
  </select>
  <delete id="deleteByPrimaryKey" parameterType="java.lang.Integer">
    <!--
      WARNING - @mbggenerated
      This element is automatically generated by MyBatis Generator, do not modify.
      This element was generated on Thu Oct 26 19:04:52 GMT+08:00 2017.
    -->
    delete from recommend_book
    where id = #{id,jdbcType=INTEGER}
  </delete>
  <delete id="deleteByExample" parameterType="com.chawuzhi.novel.common.domain.RecommendBookExample">
    <!--
      WARNING - @mbggenerated
      This element is automatically generated by MyBatis Generator, do not modify.
      This element was generated on Thu Oct 26 19:04:52 GMT+08:00 2017.
    -->
    delete from recommend_book
    <if test="_parameter != null">
      <include refid="Example_Where_Clause" />
    </if>
  </delete>
  <insert id="insert" parameterType="com.chawuzhi.novel.common.domain.RecommendBook">
    <!--
      WARNING - @mbggenerated
      This element is automatically generated by MyBatis Generator, do not modify.
      This element was generated on Thu Oct 26 19:04:52 GMT+08:00 2017.
    -->
    insert into recommend_book (id, book_id, position, 
      lay_position, length_of_recommend, creater_no, 
      create_time, modifier_no, modify_time
      )
    values (#{id,jdbcType=INTEGER}, #{bookId,jdbcType=INTEGER}, #{position,jdbcType=INTEGER}, 
      #{layPosition,jdbcType=VARCHAR}, #{lengthOfRecommend,jdbcType=DATE}, #{createrNo,jdbcType=VARCHAR}, 
      #{createTime,jdbcType=TIMESTAMP}, #{modifierNo,jdbcType=VARCHAR}, #{modifyTime,jdbcType=TIMESTAMP}
      )
  </insert>
  <insert id="insertSelective" parameterType="com.chawuzhi.novel.common.domain.RecommendBook">
    <!--
      WARNING - @mbggenerated
      This element is automatically generated by MyBatis Generator, do not modify.
      This element was generated on Thu Oct 26 19:04:52 GMT+08:00 2017.
    -->
    insert into recommend_book
    <trim prefix="(" suffix=")" suffixOverrides=",">
      <if test="id != null">
        id,
      </if>
      <if test="bookId != null">
        book_id,
      </if>
      <if test="position != null">
        position,
      </if>
      <if test="layPosition != null">
        lay_position,
      </if>
      <if test="lengthOfRecommend != null">
        length_of_recommend,
      </if>
      <if test="createrNo != null">
        creater_no,
      </if>
      <if test="createTime != null">
        create_time,
      </if>
      <if test="modifierNo != null">
        modifier_no,
      </if>
      <if test="modifyTime != null">
        modify_time,
      </if>
    </trim>
    <trim prefix="values (" suffix=")" suffixOverrides=",">
      <if test="id != null">
        #{id,jdbcType=INTEGER},
      </if>
      <if test="bookId != null">
        #{bookId,jdbcType=INTEGER},
      </if>
      <if test="position != null">
        #{position,jdbcType=INTEGER},
      </if>
      <if test="layPosition != null">
        #{layPosition,jdbcType=VARCHAR},
      </if>
      <if test="lengthOfRecommend != null">
        #{lengthOfRecommend,jdbcType=DATE},
      </if>
      <if test="createrNo != null">
        #{createrNo,jdbcType=VARCHAR},
      </if>
      <if test="createTime != null">
        #{createTime,jdbcType=TIMESTAMP},
      </if>
      <if test="modifierNo != null">
        #{modifierNo,jdbcType=VARCHAR},
      </if>
      <if test="modifyTime != null">
        #{modifyTime,jdbcType=TIMESTAMP},
      </if>
    </trim>
  </insert>
  <select id="countByExample" parameterType="com.chawuzhi.novel.common.domain.RecommendBookExample" resultType="java.lang.Integer">
    <!--
      WARNING - @mbggenerated
      This element is automatically generated by MyBatis Generator, do not modify.
      This element was generated on Thu Oct 26 19:04:52 GMT+08:00 2017.
    -->
    select count(*) from recommend_book
    <if test="_parameter != null">
      <include refid="Example_Where_Clause" />
    </if>
  </select>
  <update id="updateByExampleSelective" parameterType="map">
    <!--
      WARNING - @mbggenerated
      This element is automatically generated by MyBatis Generator, do not modify.
      This element was generated on Thu Oct 26 19:04:52 GMT+08:00 2017.
    -->
    update recommend_book
    <set>
      <if test="record.id != null">
        id = #{record.id,jdbcType=INTEGER},
      </if>
      <if test="record.bookId != null">
        book_id = #{record.bookId,jdbcType=INTEGER},
      </if>
      <if test="record.position != null">
        position = #{record.position,jdbcType=INTEGER},
      </if>
      <if test="record.layPosition != null">
        lay_position = #{record.layPosition,jdbcType=VARCHAR},
      </if>
      <if test="record.lengthOfRecommend != null">
        length_of_recommend = #{record.lengthOfRecommend,jdbcType=DATE},
      </if>
      <if test="record.createrNo != null">
        creater_no = #{record.createrNo,jdbcType=VARCHAR},
      </if>
      <if test="record.createTime != null">
        create_time = #{record.createTime,jdbcType=TIMESTAMP},
      </if>
      <if test="record.modifierNo != null">
        modifier_no = #{record.modifierNo,jdbcType=VARCHAR},
      </if>
      <if test="record.modifyTime != null">
        modify_time = #{record.modifyTime,jdbcType=TIMESTAMP},
      </if>
    </set>
    <if test="_parameter != null">
      <include refid="Update_By_Example_Where_Clause" />
    </if>
  </update>
  <update id="updateByExample" parameterType="map">
    <!--
      WARNING - @mbggenerated
      This element is automatically generated by MyBatis Generator, do not modify.
      This element was generated on Thu Oct 26 19:04:52 GMT+08:00 2017.
    -->
    update recommend_book
    set id = #{record.id,jdbcType=INTEGER},
      book_id = #{record.bookId,jdbcType=INTEGER},
      position = #{record.position,jdbcType=INTEGER},
      lay_position = #{record.layPosition,jdbcType=VARCHAR},
      length_of_recommend = #{record.lengthOfRecommend,jdbcType=DATE},
      creater_no = #{record.createrNo,jdbcType=VARCHAR},
      create_time = #{record.createTime,jdbcType=TIMESTAMP},
      modifier_no = #{record.modifierNo,jdbcType=VARCHAR},
      modify_time = #{record.modifyTime,jdbcType=TIMESTAMP}
    <if test="_parameter != null">
      <include refid="Update_By_Example_Where_Clause" />
    </if>
  </update>
  <update id="updateByPrimaryKeySelective" parameterType="com.chawuzhi.novel.common.domain.RecommendBook">
    <!--
      WARNING - @mbggenerated
      This element is automatically generated by MyBatis Generator, do not modify.
      This element was generated on Thu Oct 26 19:04:52 GMT+08:00 2017.
    -->
    update recommend_book
    <set>
      <if test="bookId != null">
        book_id = #{bookId,jdbcType=INTEGER},
      </if>
      <if test="position != null">
        position = #{position,jdbcType=INTEGER},
      </if>
      <if test="layPosition != null">
        lay_position = #{layPosition,jdbcType=VARCHAR},
      </if>
      <if test="lengthOfRecommend != null">
        length_of_recommend = #{lengthOfRecommend,jdbcType=DATE},
      </if>
      <if test="createrNo != null">
        creater_no = #{createrNo,jdbcType=VARCHAR},
      </if>
      <if test="createTime != null">
        create_time = #{createTime,jdbcType=TIMESTAMP},
      </if>
      <if test="modifierNo != null">
        modifier_no = #{modifierNo,jdbcType=VARCHAR},
      </if>
      <if test="modifyTime != null">
        modify_time = #{modifyTime,jdbcType=TIMESTAMP},
      </if>
    </set>
    where id = #{id,jdbcType=INTEGER}
  </update>
  <update id="updateByPrimaryKey" parameterType="com.chawuzhi.novel.common.domain.RecommendBook">
    <!--
      WARNING - @mbggenerated
      This element is automatically generated by MyBatis Generator, do not modify.
      This element was generated on Thu Oct 26 19:04:52 GMT+08:00 2017.
    -->
    update recommend_book
    set book_id = #{bookId,jdbcType=INTEGER},
      position = #{position,jdbcType=INTEGER},
      lay_position = #{layPosition,jdbcType=VARCHAR},
      length_of_recommend = #{lengthOfRecommend,jdbcType=DATE},
      creater_no = #{createrNo,jdbcType=VARCHAR},
      create_time = #{createTime,jdbcType=TIMESTAMP},
      modifier_no = #{modifierNo,jdbcType=VARCHAR},
      modify_time = #{modifyTime,jdbcType=TIMESTAMP}
    where id = #{id,jdbcType=INTEGER}
  </update>
</mapper>